README.md
setup.py
viewm2m/__init__.py
viewm2m/captor.py
viewm2m/viewm2m.py
viewm2m.egg-info/PKG-INFO
viewm2m.egg-info/SOURCES.txt
viewm2m.egg-info/dependency_links.txt
viewm2m.egg-info/entry_points.txt
viewm2m.egg-info/requires.txt
viewm2m.egg-info/top_level.txt